LICENSE.txt
MANIFEST.in
README.rst
setup.py
aldryn_video/__init__.py
aldryn_video/cms_plugins.py
aldryn_video/models.py
aldryn_video/tests.py
aldryn_video/utils.py
aldryn_video.egg-info/PKG-INFO
aldryn_video.egg-info/SOURCES.txt
aldryn_video.egg-info/SOURCES.txt.py
aldryn_video.egg-info/dependency_links.txt
aldryn_video.egg-info/dependency_links.txt.py
aldryn_video.egg-info/not-zip-safe
aldryn_video.egg-info/requires.txt
aldryn_video.egg-info/requires.txt.py
aldryn_video.egg-info/top_level.txt
aldryn_video.egg-info/top_level.txt.py
aldryn_video/boilerplates/.DS_Store
aldryn_video/boilerplates/bootstrap3/.DS_Store
aldryn_video/boilerplates/bootstrap3/static/img/aldryn_video/video-32x32.png
aldryn_video/boilerplates/bootstrap3/templates/aldryn_video/video.html
aldryn_video/boilerplates/legacy/.DS_Store
aldryn_video/boilerplates/legacy/static/.DS_Store
aldryn_video/boilerplates/legacy/static/img/aldryn_video/video-32x32.png
aldryn_video/boilerplates/legacy/templates/.DS_Store
aldryn_video/boilerplates/legacy/templates/aldryn_video/video.html
aldryn_video/locale/de/LC_MESSAGES/django.mo
aldryn_video/locale/de/LC_MESSAGES/django.po
aldryn_video/locale/en/LC_MESSAGES/django.mo
aldryn_video/locale/en/LC_MESSAGES/django.po
aldryn_video/locale/fr/LC_MESSAGES/django.mo
aldryn_video/locale/fr/LC_MESSAGES/django.po
aldryn_video/locale/it/LC_MESSAGES/django.mo
aldryn_video/locale/it/LC_MESSAGES/django.po
aldryn_video/migrations/0001_initial.py
aldryn_video/migrations/__init__.py
aldryn_video/south_migrations/0001_initial.py
aldryn_video/south_migrations/0002_auto__add_field_oembedvideoplugin_auto_play__add_field_oembedvideoplug.py
aldryn_video/south_migrations/0003_auto__add_field_oembedvideoplugin_use_lightbox.py
aldryn_video/south_migrations/0004_auto__del_field_oembedvideoplugin_html__add_field_oembedvideoplugin_oe.py
aldryn_video/south_migrations/0005_migrate_to_json_field.py
aldryn_video/south_migrations/0006_auto__del_field_oembedvideoplugin_use_lightbox.py
aldryn_video/south_migrations/0007_auto__add_field_oembedvideoplugin_custom_params.py
aldryn_video/south_migrations/0008_auto__add_field_oembedvideoplugin_iframe_width__add_field_oembedvideop.py
aldryn_video/south_migrations/0009_fix_tables.py
aldryn_video/south_migrations/__init__.py
aldryn_video/static/img/aldryn_video/video-32x32.png
aldryn_video/templates/aldryn_video/video.html